README.md
setup.py
monolith/__init__.py
monolith/monolith.py
monolith_lib.egg-info/PKG-INFO
monolith_lib.egg-info/SOURCES.txt
monolith_lib.egg-info/dependency_links.txt
monolith_lib.egg-info/top_level.txt