Metadata-Version: 2.2
Name: monolith_lib
Version: 0.0.4
Summary: A code execution engine
Home-page: https://github.com/Elfsong/Monolith
Author: Du Mingzhe
Author-email: dumingzhex@gmail.com
Classifier: Programming Language :: Python :: 3
Classifier: License :: OSI Approved :: MIT License
Classifier: Operating System :: OS Independent
Dynamic: author
Dynamic: author-email
Dynamic: classifier
Dynamic: description
Dynamic: description-content-type
Dynamic: home-page
Dynamic: summary
